KPZDLMSext/__init__.py
KPZDLMSext/enums.py
KPZDLMSext/parameters.py
KPZDLMSext/task.py
kpzdlmsext-0.0.10.dist-info/METADATA
kpzdlmsext-0.0.10.dist-info/WHEEL
kpzdlmsext-0.0.10.dist-info/top_level.txt
kpzdlmsext-0.0.10.dist-info/RECORD
