Metadata-Version: 2.4
Name: KPZDLMSext
Version: 0.0.10
Summary: extiontions over DLMS
Author-email: Sergei Vasilev <vasilsv@ite-ng.ru>
Project-URL: Source, https://git.ite-ng.ru/dep/kpzdlmsext_prj
Keywords: DLMS,spodes,extentions
Classifier: Programming Language :: Python :: 3
Classifier: License :: OSI Approved :: MIT License
Classifier: Operating System :: OS Independent
Requires-Python: >=3.12
Requires-Dist: DLMS_SPODES_client<0.20,>=0.19.36
Requires-Dist: SPODESext>=0.0.7
Provides-Extra: dev
Requires-Dist: mypy>=1.5.0; extra == "dev"
Requires-Dist: ruff>=0.11; extra == "dev"
Requires-Dist: types-requests; extra == "dev"
Requires-Dist: build; extra == "dev"
Requires-Dist: twine; extra == "dev"
